eqc_models-0.14.5.data/platlib/compile_extensions.py
eqc_models-0.14.5.data/platlib/eqc_models/__init__.py
eqc_models-0.14.5.data/platlib/eqc_models/decoding.py
eqc_models-0.14.5.data/platlib/eqc_models/algorithms/__init__.py
eqc_models-0.14.5.data/platlib/eqc_models/algorithms/base.py
eqc_models-0.14.5.data/platlib/eqc_models/algorithms/penaltymultiplier.py
eqc_models-0.14.5.data/platlib/eqc_models/allocation/__init__.py
eqc_models-0.14.5.data/platlib/eqc_models/allocation/allocation.py
eqc_models-0.14.5.data/platlib/eqc_models/allocation/portbase.py
eqc_models-0.14.5.data/platlib/eqc_models/allocation/portmomentum.py
eqc_models-0.14.5.data/platlib/eqc_models/assignment/__init__.py
eqc_models-0.14.5.data/platlib/eqc_models/assignment/qap.py
eqc_models-0.14.5.data/platlib/eqc_models/assignment/resource.py
eqc_models-0.14.5.data/platlib/eqc_models/assignment/setpartition.py
eqc_models-0.14.5.data/platlib/eqc_models/base/__init__.py
eqc_models-0.14.5.data/platlib/eqc_models/base/base.py
eqc_models-0.14.5.data/platlib/eqc_models/base/binaries.py
eqc_models-0.14.5.data/platlib/eqc_models/base/constraints.py
eqc_models-0.14.5.data/platlib/eqc_models/base/operators.py
eqc_models-0.14.5.data/platlib/eqc_models/base/polyeval.c
eqc_models-0.14.5.data/platlib/eqc_models/base/polyeval.cpython-310-darwin.so
eqc_models-0.14.5.data/platlib/eqc_models/base/polyeval.pyx
eqc_models-0.14.5.data/platlib/eqc_models/base/polynomial.py
eqc_models-0.14.5.data/platlib/eqc_models/base/quadratic.py
eqc_models-0.14.5.data/platlib/eqc_models/base/results.py
eqc_models-0.14.5.data/platlib/eqc_models/combinatorics/__init__.py
eqc_models-0.14.5.data/platlib/eqc_models/combinatorics/setcover.py
eqc_models-0.14.5.data/platlib/eqc_models/combinatorics/setpartition.py
eqc_models-0.14.5.data/platlib/eqc_models/graph/__init__.py
eqc_models-0.14.5.data/platlib/eqc_models/graph/base.py
eqc_models-0.14.5.data/platlib/eqc_models/graph/hypergraph.py
eqc_models-0.14.5.data/platlib/eqc_models/graph/maxcut.py
eqc_models-0.14.5.dist-info/licenses/LICENSE.txt
eqc_models-0.14.5.dist-info/METADATA
eqc_models-0.14.5.dist-info/WHEEL
eqc_models-0.14.5.dist-info/top_level.txt
eqc_models-0.14.5.dist-info/RECORD
