Metadata-Version: 2.4
Name: eqc-models
Version: 0.14.5
Summary: Optimization and ML modeling package targeting EQC devices
Author-email: "Quantum Computing Inc." <support@quantumcomputinginc.com>
Project-URL: Homepage, https://quantumcomputinginc.com
Project-URL: Documentation, https://quantumcomputinginc.com/learn/support/software-packages/
Project-URL: Issues, https://support.quantumcomputinginc.com/
Requires-Python: <3.14,>=3.9
License-File: LICENSE.txt
Requires-Dist: emucore-direct==1.0.7; python_version < "3.11"
Requires-Dist: eqc-direct==2.0.2; python_version < "3.11"
Requires-Dist: numpy<2,>=1.22.1
Requires-Dist: networkx<3,>=2.6.3
Requires-Dist: pandas<3,>=2.1.0
Requires-Dist: scikit-learn<2,>=1.2.1
Requires-Dist: lightgbm<5,>=4.6.0
Requires-Dist: xgboost<4,>=1.7.4
Requires-Dist: qci-client<6,>=5
Provides-Extra: dev
Requires-Dist: pytest<8,>=7.1.0; extra == "dev"
Requires-Dist: pytest-cov; extra == "dev"
Requires-Dist: sphinx_rtd_theme<2,>=1.3.0; extra == "dev"
Dynamic: license-file
